echaim/__init__.py
echaim/density_profile.py
echaim/echaimlib.py
echaim/helpers.py
echaim/libechaim.dylib
echaim/model_data/AACGM_coeffs/aacgm_coeffs-13-1590.asc
echaim/model_data/AACGM_coeffs/aacgm_coeffs-13-1595.asc
echaim/model_data/AACGM_coeffs/aacgm_coeffs-13-1600.asc
echaim/model_data/AACGM_coeffs/aacgm_coeffs-13-1605.asc
echaim/model_data/AACGM_coeffs/aacgm_coeffs-13-1610.asc
echaim/model_data/AACGM_coeffs/aacgm_coeffs-13-1615.asc
echaim/model_data/AACGM_coeffs/aacgm_coeffs-13-1620.asc
echaim/model_data/AACGM_coeffs/aacgm_coeffs-13-1625.asc
echaim/model_data/AACGM_coeffs/aacgm_coeffs-13-1630.asc
echaim/model_data/AACGM_coeffs/aacgm_coeffs-13-1635.asc
echaim/model_data/AACGM_coeffs/aacgm_coeffs-13-1640.asc
echaim/model_data/AACGM_coeffs/aacgm_coeffs-13-1645.asc
echaim/model_data/AACGM_coeffs/aacgm_coeffs-13-1650.asc
echaim/model_data/AACGM_coeffs/aacgm_coeffs-13-1655.asc
echaim/model_data/AACGM_coeffs/aacgm_coeffs-13-1660.asc
echaim/model_data/AACGM_coeffs/aacgm_coeffs-13-1665.asc
echaim/model_data/AACGM_coeffs/aacgm_coeffs-13-1670.asc
echaim/model_data/AACGM_coeffs/aacgm_coeffs-13-1675.asc
echaim/model_data/AACGM_coeffs/aacgm_coeffs-13-1680.asc
echaim/model_data/AACGM_coeffs/aacgm_coeffs-13-1685.asc
echaim/model_data/AACGM_coeffs/aacgm_coeffs-13-1690.asc
echaim/model_data/AACGM_coeffs/aacgm_coeffs-13-1695.asc
echaim/model_data/AACGM_coeffs/aacgm_coeffs-13-1700.asc
echaim/model_data/AACGM_coeffs/aacgm_coeffs-13-1705.asc
echaim/model_data/AACGM_coeffs/aacgm_coeffs-13-1710.asc
echaim/model_data/AACGM_coeffs/aacgm_coeffs-13-1715.asc
echaim/model_data/AACGM_coeffs/aacgm_coeffs-13-1720.asc
echaim/model_data/AACGM_coeffs/aacgm_coeffs-13-1725.asc
echaim/model_data/AACGM_coeffs/aacgm_coeffs-13-1730.asc
echaim/model_data/AACGM_coeffs/aacgm_coeffs-13-1735.asc
echaim/model_data/AACGM_coeffs/aacgm_coeffs-13-1740.asc
echaim/model_data/AACGM_coeffs/aacgm_coeffs-13-1745.asc
echaim/model_data/AACGM_coeffs/aacgm_coeffs-13-1750.asc
echaim-1.1.3.dist-info/COPYING
echaim-1.1.3.dist-info/LICENSE
echaim-1.1.3.dist-info/METADATA
echaim-1.1.3.dist-info/WHEEL
echaim-1.1.3.dist-info/RECORD
